{
    "black": {
        "x": [
            170.6,
            223.0,
            211.0,
            227.0,
            318.0,
            300.0,
            369.0
        ],
        "y": [
            184.9,
            168.0,
            214.0,
            191.0,
            172.0,
            247.0,
            231.0
        ]
    },
    "white": {
        "x": [
            324.0,
            257.0,
            261.0,
            250.0,
            241.0,
            215.0,
            217.0
        ],
        "y": [
            212.0,
            222.0,
            168.0,
            198.0,
            242.0,
            206.0,
            247.0
        ]
    }
}