{
    "black": {
        "x": [
            364.0,
            301.0,
            333.5,
            304.5,
            221.5,
            273.5,
            174.0
        ],
        "y": [
            284.0,
            272.5,
            236.5,
            236.5,
            208.0,
            155.0,
            131.0
        ]
    },
    "white": {
        "x": [
            235.5,
            242.0,
            300.5,
            274.0,
            228.0,
            311.5,
            254.0
        ],
        "y": [
            306.0,
            244.5,
            263.0,
            233.0,
            180.0,
            158.5,
            109.0
        ]
    }
}