{
    "black": {
        "x": [
            357.0,
            323.0,
            303.0,
            306.0,
            255.0,
            222.0,
            182.0
        ],
        "y": [
            180.0,
            229.0,
            167.0,
            200.0,
            254.0,
            161.0,
            207.0
        ]
    },
    "white": {
        "x": [
            277.0,
            303.0,
            245.0,
            277.0,
            308.0,
            231.0,
            254.0
        ],
        "y": [
            107.0,
            127.0,
            130.0,
            145.0,
            210.0,
            223.0,
            308.0
        ]
    }
}