{
    "black": {
        "x": [
            301.2,
            264.0,
            311.0,
            284.2,
            224.9,
            314.0,
            250.0
        ],
        "y": [
            302.0,
            261.0,
            253.0,
            229.0,
            183.0,
            150.0,
            114.0
        ]
    },
    "white": {
        "x": [
            341.0,
            304.0,
            327.0,
            305.0,
            238.0,
            275.0,
            197.70000000000005
        ],
        "y": [
            250.0,
            256.0,
            210.0,
            221.0,
            240.0,
            159.0,
            166.0
        ]
    }
}