{
    "black": {
        "x": [
            377.0,
            325.5,
            330.5,
            314.5,
            235.5,
            234.0,
            162.5
        ],
        "y": [
            228.5,
            243.0,
            188.5,
            218.0,
            251.0,
            164.0,
            179.5
        ]
    },
    "white": {
        "x": [
            305.0,
            267.5,
            234.0,
            245.0,
            239.0,
            269.0,
            279.0
        ],
        "y": [
            167.0,
            230.0,
            179.0,
            215.0,
            200.0,
            249.0,
            190.5
        ]
    }
}